heroku_audit/__init__.py
heroku_audit/__main__.py
heroku_audit/client.py
heroku_audit/config.py
heroku_audit/format.py
heroku_audit/options.py
heroku_audit/style.py
heroku_audit/utils.py
heroku_audit/cli/__init__.py
heroku_audit/cli/apps.py
heroku_audit/cli/env.py
heroku_audit/cli/postgres.py
heroku_audit/cli/redis.py
heroku_audit/cli/users.py
heroku_audit-0.0.3.dist-info/entry_points.txt
heroku_audit-0.0.3.dist-info/LICENSE
heroku_audit-0.0.3.dist-info/WHEEL
heroku_audit-0.0.3.dist-info/METADATA
heroku_audit-0.0.3.dist-info/RECORD
