Metadata-Version: 2.3
Name: heroku-audit
Version: 0.0.3
Summary: Command-line tool for reporting on specific attributes of a Heroku environment.
Author-email: Jake Howard <jake.howard@torchbox.com>
Requires-Python: >=3.9
Classifier: License :: OSI Approved
Classifier: License :: OSI Approved :: BSD License
Classifier: Development Status :: 5 - Production/Stable
Classifier: Environment :: Console
Classifier: Topic :: Utilities
Classifier: Topic :: System :: Systems Administration
Classifier: Programming Language :: Python :: 3
Classifier: Programming Language :: Python :: 3.9
Classifier: Programming Language :: Python :: 3.10
Classifier: Programming Language :: Python :: 3.11
Classifier: Programming Language :: Python :: 3.12
Classifier: Programming Language :: Python :: 3.13
Classifier: Intended Audience :: System Administrators
Classifier: Intended Audience :: Developers
Classifier: Operating System :: OS Independent
Classifier: Natural Language :: English
Classifier: Typing :: Typed
Requires-Dist: heroku3==5.2.1
Requires-Dist: typer==0.13.1
Requires-Dist: rich==13.9.4
Requires-Dist: python-dotenv==1.0.1
Requires-Dist: ruff==0.7.4 ; extra == "dev"
Requires-Dist: mypy==1.13.0 ; extra == "dev"
Requires-Dist: types-requests ; extra == "dev"
Project-URL: Changelog, https://github.com/torchbox/heroku-audit/releases
Project-URL: Issues, https://github.com/torchbox/heroku-audit/issues
Project-URL: Source, https://github.com/torchbox/heroku-audit
Provides-Extra: dev
